cognito_client/__init__.py
cognito_client/cognito_client.py
cognito_client-0.0.1.dist-info/LICENSE
cognito_client-0.0.1.dist-info/METADATA
cognito_client-0.0.1.dist-info/WHEEL
cognito_client-0.0.1.dist-info/top_level.txt
cognito_client-0.0.1.dist-info/RECORD
