Metadata-Version: 2.1
Name: cognito-client
Version: 0.0.1
Summary: A small example package
Home-page: https://github.com/developmentseed/cognito_client
Author: Anthony Lukach
Author-email: Anthony Lukach <anthony@developmentseed.com>, Aimee Barciauskas <aimee@developmentseed.com>
License: MIT
Project-URL: Homepage, https://github.com/developmentseed/cognito_client
Project-URL: Bug Tracker, https://github.com/developmentseed/cognito_client/issues
Keywords: Cognito AWS
Classifier: Programming Language :: Python :: 3
Classifier: License :: OSI Approved :: MIT License
Classifier: Operating System :: OS Independent
Requires-Python: >=3.7
License-File: LICENSE
Requires-Dist: aws-cdk-lib (==2.27.0)
Requires-Dist: aws-cdk.aws-cognito-identitypool-alpha (==2.27.0a0)
Requires-Dist: constructs (<11.0.0,>=10.0.0)
Requires-Dist: pydantic (==1.9.1)
Requires-Dist: black (==22.3.0)
Requires-Dist: boto3 (==1.24.15)
Requires-Dist: boto3-stubs[cognito-identity,cognito-idp]
Provides-Extra: test
Requires-Dist: pytest ; extra == 'test'
